abstract_mode.py
bot.py
characters.py
client_config.py
config.py
direct_input.py
font_loader.py
gui.py
levels.py
menu.py
test_pytest.py
utils.py
windows.py
BHBot_master-2.1.dist-info/LICENSE
BHBot_master-2.1.dist-info/METADATA
BHBot_master-2.1.dist-info/WHEEL
BHBot_master-2.1.dist-info/top_level.txt
BHBot_master-2.1.dist-info/RECORD
